tuilwindcss/__init__.py
tuilwindcss/__main__.py
tuilwindcss/constants.py
tuilwindcss/construct.py
tuilwindcss-0.1.0.dist-info/METADATA
tuilwindcss-0.1.0.dist-info/WHEEL
tuilwindcss-0.1.0.dist-info/top_level.txt
tuilwindcss-0.1.0.dist-info/RECORD
