Metadata-Version: 2.1
Name: tuilwindcss
Version: 0.1.0
Author: Vincent D. Warmerdam
Classifier: Intended Audience :: Science/Research
Classifier: Programming Language :: Python :: 3
Classifier: Programming Language :: Python :: 3.8
Classifier: Programming Language :: Python :: 3.9
Classifier: Programming Language :: Python :: 3.10
Classifier: License :: OSI Approved :: MIT License
Requires-Dist: textual (>=0.13.0)
Requires-Dist: radicli (>=0.0.15)
Requires-Dist: srsly (>=2.4.6)
Requires-Dist: parse (>=1.19.0)
Provides-Extra: dev
Requires-Dist: pytest (>=5.4.3) ; extra == 'dev'
Requires-Dist: black (>=19.10b0) ; extra == 'dev'
Requires-Dist: flake8 (>=3.8.3) ; extra == 'dev'
Requires-Dist: mktestdocs (>=0.1.0) ; extra == 'dev'
Requires-Dist: interrogate (>=1.2.0) ; extra == 'dev'
Requires-Dist: isort (==5.12.0) ; extra == 'dev'
Requires-Dist: autoflake (==2.0.1) ; extra == 'dev'
